gwdetchar/__init__.py
gwdetchar/_version.py
gwdetchar/conftest.py
gwdetchar/conlog.py
gwdetchar/const.py
gwdetchar/mct.py
gwdetchar/overflow.py
gwdetchar/io/__init__.py
gwdetchar/io/datafind.py
gwdetchar/io/html.py
gwdetchar/io/ligolw.py
gwdetchar/io/tests/__init__.py
gwdetchar/io/tests/test_datafind.py
gwdetchar/io/tests/test_html.py
gwdetchar/io/tests/test_ligolw.py
gwdetchar/lasso/__init__.py
gwdetchar/lasso/__main__.py
gwdetchar/lasso/core.py
gwdetchar/lasso/old.py
gwdetchar/lasso/plot.py
gwdetchar/lasso/tests/__init__.py
gwdetchar/lasso/tests/test_core.py
gwdetchar/lasso/tests/test_main.py
gwdetchar/lasso/tests/test_plot.py
gwdetchar/nagios/__init__.py
gwdetchar/nagios/__main__.py
gwdetchar/nagios/core.py
gwdetchar/nagios/tests/__init__.py
gwdetchar/nagios/tests/test_main.py
gwdetchar/omega/__init__.py
gwdetchar/omega/__main__.py
gwdetchar/omega/batch.py
gwdetchar/omega/config.py
gwdetchar/omega/core.py
gwdetchar/omega/html.py
gwdetchar/omega/plot.py
gwdetchar/omega/tests/__init__.py
gwdetchar/omega/tests/test_batch.py
gwdetchar/omega/tests/test_config.py
gwdetchar/omega/tests/test_core.py
gwdetchar/omega/tests/test_html.py
gwdetchar/omega/tests/test_main.py
gwdetchar/omega/tests/test_plot.py
gwdetchar/saturation/__init__.py
gwdetchar/saturation/__main__.py
gwdetchar/saturation/core.py
gwdetchar/saturation/tests/__init__.py
gwdetchar/saturation/tests/test_saturation.py
gwdetchar/scattering/__init__.py
gwdetchar/scattering/__main__.py
gwdetchar/scattering/core.py
gwdetchar/scattering/plot.py
gwdetchar/scattering/simple.py
gwdetchar/scattering/tests/__init__.py
gwdetchar/scattering/tests/test_core.py
gwdetchar/scattering/tests/test_main.py
gwdetchar/scattering/tests/test_plot.py
gwdetchar/scattering/tests/test_simple.py
gwdetchar/tests/__init__.py
gwdetchar/tests/test_conlog.py
gwdetchar/tests/test_const.py
gwdetchar/utils/__init__.py
gwdetchar/utils/cds.py
gwdetchar/utils/cli.py
gwdetchar/utils/condor.py
gwdetchar/utils/daq.py
gwdetchar/utils/plot.py
gwdetchar-2.3.3.dist-info/licenses/LICENSE
gwdetchar-2.3.3.dist-info/METADATA
gwdetchar-2.3.3.dist-info/WHEEL
gwdetchar-2.3.3.dist-info/entry_points.txt
gwdetchar-2.3.3.dist-info/top_level.txt
gwdetchar-2.3.3.dist-info/RECORD
