Metadata-Version: 2.4
Name: gwdetchar
Version: 2.3.3
Summary: A python package for gravitational-wave detector characterisation
Author-email: Alex Urban <alex.urban@ligo.org>, Duncan Macleod <duncan.macleod@ligo.org>
Maintainer-email: Evan Goetz <evan.goetz@ligo.org>
License-Expression: GPL-3.0-or-later
Project-URL: Documentation, https://gwdetchar.readthedocs.io
Project-URL: Source Code, https://github.com/gwdetchar/gwdetchar
Project-URL: Bug Tracker, https://github.com/gwdetchar/gwdetchar/issues
Project-URL: Discussion Forum, https://gwdetchar.slack.com
Classifier: Development Status :: 5 - Production/Stable
Classifier: Intended Audience :: Developers
Classifier: Intended Audience :: Science/Research
Classifier: Natural Language :: English
Classifier: Operating System :: OS Independent
Classifier: Programming Language :: Python
Classifier: Programming Language :: Python :: 3
Classifier: Programming Language :: Python :: 3.9
Classifier: Programming Language :: Python :: 3.10
Classifier: Programming Language :: Python :: 3.11
Classifier: Topic :: Scientific/Engineering
Classifier: Topic :: Scientific/Engineering :: Astronomy
Classifier: Topic :: Scientific/Engineering :: Physics
Requires-Python: >=3.9
License-File: LICENSE
Requires-Dist: astropy>=3.0.0
Requires-Dist: beautifulsoup4
Requires-Dist: coloredlogs
Requires-Dist: gwdatafind
Requires-Dist: gwpy>=3.0.10
Requires-Dist: gwtrigfind
Requires-Dist: lalsuite
Requires-Dist: lxml
Requires-Dist: MarkupPy>=1.14
Requires-Dist: matplotlib>=3.9
Requires-Dist: numpy>=1.16
Requires-Dist: pandas
Requires-Dist: pycondor
Requires-Dist: pygments>=2.7.3
Requires-Dist: igwn-ligolw
Requires-Dist: pytz
Requires-Dist: scikit-learn
Requires-Dist: scipy>=1.2.0
Provides-Extra: test
Requires-Dist: flake8; extra == "test"
Requires-Dist: pygments>=2.19.0; extra == "test"
Requires-Dist: pytest>=3.3.0; extra == "test"
Requires-Dist: pytest-cov>=2.4.0; extra == "test"
Provides-Extra: doc
Requires-Dist: numpydoc; extra == "doc"
Requires-Dist: sphinx; extra == "doc"
Requires-Dist: sphinx_bootstrap_theme; extra == "doc"
Requires-Dist: sphinxcontrib-programoutput; extra == "doc"
Dynamic: license-file
